Demo/main.py
TaloGameServicesApi/__init__.py
TaloGameServicesApi/py.typed
TaloGameServicesApi/version.py
TaloGameServicesApi/Api/BaseApi.py
TaloGameServicesApi/Api/PlayerApi.py
TaloGameServicesApi/Api/PlayerAuthAPI.py
TaloGameServicesApi/Api/__init__.py
TaloGameServicesApi/Types/Prop.py
TaloGameServicesApi-0.1.0.dist-info/LICENSE
TaloGameServicesApi-0.1.0.dist-info/METADATA
TaloGameServicesApi-0.1.0.dist-info/WHEEL
TaloGameServicesApi-0.1.0.dist-info/top_level.txt
TaloGameServicesApi-0.1.0.dist-info/RECORD
